{
  "generated_at": "2026-02-17T03:58:40.629Z",
  "dry_run": false,
  "source_root": "docs/thc-site-pictures",
  "products_file": "docs/product-media.tsv",
  "variants_file": "docs/variant-media.tsv",
  "prep_report_file": "docs/media-prepare-report.json",
  "counts": {
    "product_handles": 20,
    "variant_skus": 70,
    "sku_media_dirs": 70,
    "sku_media_with_assets": 70,
    "variant_rows_written": 70,
    "product_rows_written": 20
  },
  "renamed_dirs": [],
  "rename_conflicts": [],
  "missing_sku_dirs": [],
  "missing_assets": [],
  "used_full_for_thumbnail": [
    "tnc-fs-cbd-500",
    "tnc-fs-cbd-1000",
    "tnc-fs-cbd-2500",
    "tnc-fs-cbd-5000",
    "tnc-bs-cbd-500",
    "tnc-bs-cbd-1000",
    "tnc-bs-cbd-2500",
    "tnc-bs-cbd-5000",
    "cap-iso-cbd-25-30ct",
    "cap-iso-cbd-50-30ct",
    "gum-bs-cbd-25-4ct",
    "gum-bs-cbd-25-30ct",
    "gum-bs-cbd-25-100ct",
    "gum-bs-cbd-50-4ct",
    "gum-bs-cbd-50-30ct",
    "gum-bs-cbd-50-100ct",
    "gum-bs-cbd-25-4ct-mel",
    "gum-bs-cbd-25-30ct-mel",
    "gum-bs-cbd-25-100ct-mel",
    "gum-bs-cbd-50-4ct-mel",
    "gum-bs-cbd-50-30ct-mel",
    "gum-bs-cbd-50-100ct-mel",
    "gum-bs-cbg-25-4ct",
    "gum-bs-cbg-25-30ct",
    "gum-bs-cbg-25-100ct",
    "gum-bs-cbg-25-4ct-b12",
    "gum-bs-cbg-25-30ct-b12",
    "gum-bs-cbg-25-100ct-b12",
    "sal-iso-cbd-500-1oz",
    "sal-iso-cbd-100-5g",
    "lot-iso-cbd-500-6oz",
    "sal-fs-cbd-500-1oz",
    "sal-fs-cbd-100-5g",
    "rol-bs-cbd-2000-cool",
    "rol-bs-cbd-2000-cool-6ct",
    "rol-bs-cbd-2000-warm",
    "rol-bs-cbd-2000-warm-6ct",
    "bat-cbd-35-calm",
    "bat-cbd-35-soothe",
    "bat-cbd-100-pure",
    "d9-gum-12-10ct",
    "d9-gum-12-30ct",
    "d9-gum-12-100ct",
    "d9-gum-30-4ct",
    "d9-gum-30-30ct",
    "d9-gum-50-2ct",
    "d9-gum-50-20ct",
    "d9-drk-420-bluerazz",
    "d9-drk-420-trop",
    "d9-drk-420-pine",
    "d9-drk-420-bcherry",
    "d9-drk-420-bloodorg",
    "d9-drk-420-watermel",
    "d9-drk-50-bluerazz-40ct",
    "d9-drk-50-pine-40ct",
    "d9-drk-50-trop-40ct",
    "d9-drk-50-pinklem-40ct",
    "d9-drk-50-bluerazz-1ct",
    "d9-drk-50-pinklem-1ct",
    "d9-drk-50-trop-1ct",
    "d9-drk-50-pine-1ct",
    "d9-cer-160-lucky",
    "d9-cer-160-cinn",
    "d9-cer-160-cocoa",
    "d9-cer-160-rice",
    "d9-cer-160-apple",
    "d9-cer-160-reeses",
    "d9-cer-160-fruit",
    "d9-coo-100-chocchunk",
    "d9-brn-320-brownie"
  ],
  "empty_product_dirs": [],
  "filename_anomalies": []
}
